package nl.sander.beejava;

public class JavaOpcodes {
    public static final int LDC = 0x12;
    public static final int LDC_W = 0x13;
    public static final int LDC2_W = 0x14;

    public static final int ALOAD_0 = 0x2a;
    public static final int RETURN = 0xb1;
    public static final int GETSTATIC = 0xb2;
    public static final int GETFIELD = 0xb4;

    public static final int INVOKEINTERFACE = 0xb5;
    public static final int INVOKEVIRTUAL = 0xb6;
    public static final int INVOKESPECIAL = 0xb7;
    public static final int INVOKESTATIC = 0xb8;
    public static final int INVOKEDYNAMIC = 0xba;

}
