Classfile /Users/Shautvast/IdeaProjects/beejava/target/test-classes/nl/sander/beejava/testclasses/BeanWithClassReferences.class
  Last modified 10 Nov 2020; size 655 bytes
  SHA-256 checksum 1bb4b80be80051827e68106c7ec72140696f105df82dfc28147eaaff73a9b667
  Compiled from "BeanWithClassReferences.java"
public class nl.sander.beejava.testclasses.BeanWithClassReferences
  minor version: 0
  major version: 58
  flags: (0x0021) ACC_PUBLIC, ACC_SUPER
  this_class: #23                         // nl/sander/beejava/testclasses/BeanWithClassReferences
  super_class: #2                         // java/lang/Object
  interfaces: 0, fields: 0, methods: 3, attributes: 1
Constant pool:
   #1 = Methodref          #2.#3          // java/lang/Object."<init>":()V
   #2 = Class              #4             // java/lang/Object
   #3 = NameAndType        #5:#6          // "<init>":()V
   #4 = Utf8               java/lang/Object
   #5 = Utf8               <init>
   #6 = Utf8               ()V
   #7 = Fieldref           #8.#9          // java/lang/System.out:Ljava/io/PrintStream;
   #8 = Class              #10            // java/lang/System
   #9 = NameAndType        #11:#12        // out:Ljava/io/PrintStream;
  #10 = Utf8               java/lang/System
  #11 = Utf8               out
  #12 = Utf8               Ljava/io/PrintStream;
  #13 = String             #14            // 1
  #14 = Utf8               1
  #15 = Methodref          #16.#17        // java/io/PrintStream.println:(Ljava/lang/String;)V
  #16 = Class              #18            // java/io/PrintStream
  #17 = NameAndType        #19:#20        // println:(Ljava/lang/String;)V
  #18 = Utf8               java/io/PrintStream
  #19 = Utf8               println
  #20 = Utf8               (Ljava/lang/String;)V
  #21 = String             #22            // 2
  #22 = Utf8               2
  #23 = Class              #24            // nl/sander/beejava/testclasses/BeanWithClassReferences
  #24 = Utf8               nl/sander/beejava/testclasses/BeanWithClassReferences
  #25 = Utf8               Code
  #26 = Utf8               LineNumberTable
  #27 = Utf8               LocalVariableTable
  #28 = Utf8               this
  #29 = Utf8               Lnl/sander/beejava/testclasses/BeanWithClassReferences;
  #30 = Utf8               print1
  #31 = Utf8               print2
  #32 = Utf8               SourceFile
  #33 = Utf8               BeanWithClassReferences.java
{
  public nl.sander.beejava.testclasses.BeanWithClassReferences();
    descriptor: ()V
    flags: (0x0001) ACC_PUBLIC
    Code:
      stack=1, locals=1, args_size=1
         0: aload_0
         1: invokespecial #1                  // Method java/lang/Object."<init>":()V
         4: return
      LineNumberTable:
        line 3: 0
      LocalVariableTable:
        Start  Length  Slot  Name   Signature
            0       5     0  this   Lnl/sander/beejava/testclasses/BeanWithClassReferences;

  public void print1();
    descriptor: ()V
    flags: (0x0001) ACC_PUBLIC
    Code:
      stack=2, locals=1, args_size=1
         0: getstatic     #7                  // Field java/lang/System.out:Ljava/io/PrintStream;
         3: ldc           #13                 // String 1
         5: invokevirtual #15                 // Method java/io/PrintStream.println:(Ljava/lang/String;)V
         8: return
      LineNumberTable:
        line 6: 0
        line 7: 8
      LocalVariableTable:
        Start  Length  Slot  Name   Signature
            0       9     0  this   Lnl/sander/beejava/testclasses/BeanWithClassReferences;

  public void print2();
    descriptor: ()V
    flags: (0x0001) ACC_PUBLIC
    Code:
      stack=2, locals=1, args_size=1
         0: getstatic     #7                  // Field java/lang/System.out:Ljava/io/PrintStream;
         3: ldc           #21                 // String 2
         5: invokevirtual #15                 // Method java/io/PrintStream.println:(Ljava/lang/String;)V
         8: return
      LineNumberTable:
        line 10: 0
        line 11: 8
      LocalVariableTable:
        Start  Length  Slot  Name   Signature
            0       9     0  this   Lnl/sander/beejava/testclasses/BeanWithClassReferences;
}
SourceFile: "BeanWithClassReferences.java"